polyquad/__init__.py
polyquad/_antonietti.py
polyquad/_main.py
polyquad/_mapping.py
polyquad/_moment_matching_2d.py
polyquad/_moment_matching_3d.py
polyquad/_utils.py
polyquad-1.2.6.dist-info/LICENSE
polyquad-1.2.6.dist-info/METADATA
polyquad-1.2.6.dist-info/WHEEL
polyquad-1.2.6.dist-info/top_level.txt
polyquad-1.2.6.dist-info/RECORD
