Metadata-Version: 2.2
Name: polyquad
Version: 1.2.6
Summary: Frugal generation of quadrature for polytopal domain
Author: christophe langlois, thijs van putten, hadrien beriot, elke deckers
Author-email: christophe.langlois@kuleuven.be
Maintainer: christophe langlois
Maintainer-email: christophe.langlois@kuleuven.be
License: MIT License
Project-URL: Homepage, https://github.com/LMSD-KULeuven/polyquad
Keywords: quadrature,cubature,integration,scheme,polygon,polyhedron,polytope,polytopal,polytopic
Classifier: Programming Language :: Python :: 3
Classifier: License :: OSI Approved :: MIT License
Classifier: Operating System :: OS Independent
Requires-Python: <3.13
License-File: LICENSE
Requires-Dist: numpy<=1.26
Requires-Dist: scipy
Requires-Dist: numba
